algpro/__init__.py
algpro/algpro.py
algpro-0.0.3.dist-info/LICENSE
algpro-0.0.3.dist-info/METADATA
algpro-0.0.3.dist-info/WHEEL
algpro-0.0.3.dist-info/top_level.txt
algpro-0.0.3.dist-info/RECORD
