Metadata-Version: 2.1
Name: algpro
Version: 0.0.3
Summary: 欢迎使用灰块工作室的“简约库” Lanpasby
Home-page: https://github.com/pypa/sampleproject
Author: algfwq
Author-email: huibubu2022@163.com
License: UNKNOWN
Project-URL: Bug Tracker, https://github.com/pypa/sampleproject/issues
Platform: UNKNOWN
Classifier: Programming Language :: Python :: 3
Classifier: License :: OSI Approved :: MIT License
Classifier: Operating System :: OS Independent
Requires-Python: >=3.6
License-File: LICENSE
